{
  "predictors": [
    "close",
    "volume",
    "open",
    "high",
    "low",
    "edit_count",
    "sentiment",
    "neg_sentiment",
    "close_ratio_2",
    "trend_2",
    "edit_2",
    "close_ratio_7",
    "trend_7",
    "edit_7",
    "close_ratio_60",
    "trend_60",
    "edit_60",
    "close_ratio_365",
    "trend_365",
    "edit_365"
  ],
  "feature_names": [
    "close",
    "volume",
    "open",
    "high",
    "low",
    "edit_count",
    "sentiment",
    "neg_sentiment",
    "close_ratio_2",
    "trend_2",
    "edit_2",
    "close_ratio_7",
    "trend_7",
    "edit_7",
    "close_ratio_60",
    "trend_60",
    "edit_60",
    "close_ratio_365",
    "trend_365",
    "edit_365"
  ],
  "training_date": "2025-12-13T03:18:09.487936",
  "training_samples": 4105,
  "backtest_precision": 0.5188155459592844,
  "backtest_accuracy": 0.5056478405315614,
  "data_date_range": {
    "start": "2014-09-17 00:00:00",
    "end": "2025-12-13 00:00:00"
  }
}